{
  "project_info": {
    "project_number": "360791376391",
    "project_id": "safedrive-2025",
    "storage_bucket": "safedrive-2025.firebasestorage.app"
  },
  "client": [
    {
      "client_info": {
        "mobilesdk_app_id": "1:360791376391:android:8efd7577c6f3fb6734a0a2",
        "android_client_info": {
          "package_name": "com.example.safedrive"
        }
      },
      "oauth_client": [],
      "api_key": [
        {
          "current_key": "AIzaSyCyY85P1PJOQm2dK5EwPBtlWbk9YDSgBQ4"
        }
      ],
      "services": {
        "appinvite_service": {
          "other_platform_oauth_client": []
        }
      }
    }
  ],
  "configuration_version": "1"
}